tract_python-0.2.12.dist-info/METADATA
tract_python-0.2.12.dist-info/WHEEL
tract_python-0.2.12.dist-info/license_files/LICENSE
tract_python/__init__.py
tract_python/tract_python/__init__.py
tract_python/tract_python/ffi.py
tract_python/tract_python/native.so
tract_python-0.2.12.dist-info/RECORD
