Metadata-Version: 2.1
Name: tract-python
Version: 0.2.12
Classifier: Programming Language :: Rust
Classifier: Programming Language :: Python :: Implementation :: CPython
Classifier: Programming Language :: Python :: Implementation :: PyPy
Classifier: Intended Audience :: Developers
Classifier: Natural Language :: English
Requires-Dist: cffi>=1.15.0
Requires-Dist: numpy>=1.20.0
Requires-Dist: black; extra == 'dev'
Requires-Dist: bumpver; extra == 'dev'
Requires-Dist: isort; extra == 'dev'
Requires-Dist: pip-tools; extra == 'dev'
Requires-Dist: pytest; extra == 'dev'
Provides-Extra: dev
License-File: LICENSE
Summary: bindings of sonos/tract rust NN inference enging for python
Keywords: tract,neural network engine,deep learning
Author: Julien Balian <julien.balian@sonos.com>
Author-email: Julien Balian <julien.balian@sonos.com>
Requires-Python: >=3.7
Project-URL: Homepage, https://github.com/DreamerMind/tract-python
